practice/__init__.py
practice/bank.py
practice22-0.2.dist-info/License.txt
practice22-0.2.dist-info/METADATA
practice22-0.2.dist-info/WHEEL
practice22-0.2.dist-info/top_level.txt
practice22-0.2.dist-info/RECORD
