Metadata-Version: 2.1
Name: practice22
Version: 0.2
Summary: MegaBank Inc.s OOP-based banking system package
Author: vaishnavi
Author-email: nvaishnavi335@gmail.com
License: MIT
License-File: License.txt
Requires-Dist: pandas
Requires-Dist: requests
